LICENSE
MANIFEST.in
README.rst
setup.py
swagger_coverage_py/__init__.py
swagger_coverage_py/listener.py
swagger_coverage_py/reporter.py
swagger_coverage_py.egg-info/PKG-INFO
swagger_coverage_py.egg-info/SOURCES.txt
swagger_coverage_py.egg-info/dependency_links.txt
swagger_coverage_py.egg-info/requires.txt
swagger_coverage_py.egg-info/top_level.txt
swagger_coverage_py/swagger-coverage-commandline/bin/swagger-coverage-commandline
swagger_coverage_py/swagger-coverage-commandline/bin/swagger-coverage-commandline.bat
swagger_coverage_py/swagger-coverage-commandline/lib/activation-1.1.jar
swagger_coverage_py/swagger-coverage-commandline/lib/animal-sniffer-annotations-1.17.jar
swagger_coverage_py/swagger-coverage-commandline/lib/btf-1.2.jar
swagger_coverage_py/swagger-coverage-commandline/lib/btf-1.3.jar
swagger_coverage_py/swagger-coverage-commandline/lib/checker-compat-qual-2.5.2.jar
swagger_coverage_py/swagger-coverage-commandline/lib/checker-compat-qual-2.5.5.jar
swagger_coverage_py/swagger-coverage-commandline/lib/commons-codec-1.9.jar
swagger_coverage_py/swagger-coverage-commandline/lib/commons-io-2.4.jar
swagger_coverage_py/swagger-coverage-commandline/lib/commons-io-2.6.jar
swagger_coverage_py/swagger-coverage-commandline/lib/commons-lang3-3.2.1.jar
swagger_coverage_py/swagger-coverage-commandline/lib/commons-lang3-3.7.jar
swagger_coverage_py/swagger-coverage-commandline/lib/commons-logging-1.2.jar
swagger_coverage_py/swagger-coverage-commandline/lib/error_prone_annotations-2.2.0.jar
swagger_coverage_py/swagger-coverage-commandline/lib/error_prone_annotations-2.3.4.jar
swagger_coverage_py/swagger-coverage-commandline/lib/failureaccess-1.0.1.jar
swagger_coverage_py/swagger-coverage-commandline/lib/freemarker-2.3.29.jar
swagger_coverage_py/swagger-coverage-commandline/lib/freemarker-2.3.31.jar
swagger_coverage_py/swagger-coverage-commandline/lib/guava-27.0.1-android.jar
swagger_coverage_py/swagger-coverage-commandline/lib/guava-28.2-android.jar
swagger_coverage_py/swagger-coverage-commandline/lib/httpclient-4.5.2.jar
swagger_coverage_py/swagger-coverage-commandline/lib/httpcore-4.4.4.jar
swagger_coverage_py/swagger-coverage-commandline/lib/j2objc-annotations-1.1.jar
