Metadata-Version: 2.1
Name: swagger-coverage-py
Version: 2.1.2
Summary: Python adapter for "swagger-coverage" tool
Home-page: https://github.com/JamalZeynalov/swagger-coverage-py
Author: Jamal Zeinalov
Author-email: jamal.zeynalov@gmail.com
Classifier: Programming Language :: Python :: 3
Classifier: License :: OSI Approved :: MIT License
Classifier: Operating System :: OS Independent
Requires-Python: >=3.6
License-File: LICENSE
Requires-Dist: requests>=2.25.1
Requires-Dist: Faker>=6.0.0
